pydapsys/__init__.py
pydapsys/binaryreader.py
pydapsys/file.py
pydapsys/neo_converters/__init__.py
pydapsys/neo_converters/helper.py
pydapsys/neo_converters/interface.py
pydapsys/neo_converters/ni_pulse_stim.py
pydapsys/page.py
pydapsys/read.py
pydapsys/toc/__init__.py
pydapsys/toc/display.py
pydapsys/toc/entry.py
pydapsys/toc/exceptions.py
pydapsys/util/__init__.py
pydapsys/util/floats.py
pydapsys/util/structs.py
pydapsys-0.2.1.dist-info/LICENSE
pydapsys-0.2.1.dist-info/METADATA
pydapsys-0.2.1.dist-info/WHEEL
pydapsys-0.2.1.dist-info/RECORD
