Metadata-Version: 2.1
Name: pydapsys
Version: 0.2.1
Summary: Read recordings made with DAPSYS
Home-page: https://github.com/Digital-C-Fiber/PyDapsys
License: BSD-3-Clause
Keywords: microneurography,dapsys,neurophysiology,electrophysiology
Author: Peter Konradi
Author-email: codingchipmunk@posteo.net
Requires-Python: >=3.8,<4.0
Classifier: Development Status :: 4 - Beta
Classifier: Intended Audience :: Developers
Classifier: Intended Audience :: Healthcare Industry
Classifier: Intended Audience :: Science/Research
Classifier: License :: OSI Approved :: BSD License
Classifier: Programming Language :: Python :: 3
Classifier: Programming Language :: Python :: 3.8
Classifier: Programming Language :: Python :: 3.9
Classifier: Programming Language :: Python :: 3.10
Classifier: Programming Language :: Python :: 3.11
Classifier: Programming Language :: Python :: 3 :: Only
Provides-Extra: neo
Requires-Dist: neo (>=0.12,<1) ; extra == "neo"
Requires-Dist: numpy (>=1.21,<2.0)
Project-URL: Repository, https://github.com/Digital-C-Fiber/PyDapsys
